{"stats":{"minecraft:custom":{"minecraft:time_since_rest":37016,"minecraft:pig_one_cm":187405,"minecraft:crouch_one_cm":72,"minecraft:play_one_minute":37016,"minecraft:sprint_one_cm":13193,"minecraft:walk_one_cm":17768,"minecraft:sneak_time":241,"minecraft:mob_kills":1,"minecraft:drop":1,"minecraft:jump":37,"minecraft:damage_dealt":219,"minecraft:leave_game":2,"minecraft:walk_on_water_one_cm":1367,"minecraft:time_since_death":37016,"minecraft:climb_one_cm":1474,"minecraft:tune_noteblock":1,"minecraft:fly_one_cm":464740},"minecraft:dropped":{"minecraft:turtle_helmet":1},"minecraft:killed":{"minecraft:wither_skeleton":1},"minecraft:picked_up":{"minecraft:pufferfish":1,"minecraft:bone":2,"minecraft:shroomlight":1,"minecraft:warped_wart_block":2,"minecraft:warped_stem":1,"minecraft:porkchop":11,"minecraft:saddle":6,"minecraft:string":1},"minecraft:used":{"minecraft:netherite_sword":10,"minecraft:potion":6,"minecraft:wolf_spawn_egg":26,"minecraft:pufferfish_bucket":1,"minecraft:tnt":8,"minecraft:flint_and_steel":15,"minecraft:red_bed":24,"minecraft:carrot_on_a_stick":67,"minecraft:pig_spawn_egg":7,"minecraft:splash_potion":221}},"DataVersion":2586}